pcsv/__init__.py
pcsv/any2csv.py
pcsv/pcsv.py
pcsv/pindent.py
pcsv/plook.py
pcsv/utils.py
python_csv_demjson3-0.0.17.data/scripts/any2csv
python_csv_demjson3-0.0.17.data/scripts/pagg
python_csv_demjson3-0.0.17.data/scripts/pcat
python_csv_demjson3-0.0.17.data/scripts/pconcat
python_csv_demjson3-0.0.17.data/scripts/pcsv
python_csv_demjson3-0.0.17.data/scripts/pgraph
python_csv_demjson3-0.0.17.data/scripts/pindent
python_csv_demjson3-0.0.17.data/scripts/pjoin
python_csv_demjson3-0.0.17.data/scripts/plook
python_csv_demjson3-0.0.17.data/scripts/pset
python_csv_demjson3-0.0.17.data/scripts/psort
python_csv_demjson3-0.0.17.data/scripts/ptable
python_csv_demjson3-0.0.17.data/scripts/ptr
python_csv_demjson3-0.0.17.dist-info/METADATA
python_csv_demjson3-0.0.17.dist-info/WHEEL
python_csv_demjson3-0.0.17.dist-info/top_level.txt
python_csv_demjson3-0.0.17.dist-info/RECORD
