Metadata-Version: 2.1
Name: python-csv-demjson3
Version: 0.0.17
Summary: Python tools for manipulating csv files. This package resolves demjson/setuptools issue with original python-csv developed by Jason Trigg and support Python 3.12.6
Home-page: https://github.com/jasontrigg0/python-csv
Download-URL: https://github.com/jasontrigg0/python-csv/tarball/0.0.13
Author: Jason Trigg
Author-email: jasontrigg0@gmail.com
Requires-Dist: argparse
Requires-Dist: numpy
Requires-Dist: pandas
Requires-Dist: matplotlib
Requires-Dist: xlrd
Requires-Dist: xmltodict
Requires-Dist: demjson3
Requires-Dist: python-Levenshtein
Requires-Dist: jtutils
